{
  "ai_obsidian_config": {
    "version": "1.0",
    "created": "2025-06-20T13:40:08Z",
    "system_info": {
      "platform": "Windows",
      "shell": "pwsh",
      "shell_version": "5.1.19041.5965",
      "home_directory": "C:\\Users\\Admin",
      "current_working_directory": "C:\\Users\\Admin\\Documents\\Obsidian Vault"
    },
    "vault_config": {
      "vault_path": "C:\\Users\\Admin\\Documents\\Obsidian Vault",
      "vault_name": "Admin's Obsidian Vault",
      "file_naming_convention": "[Topic]-[Type]-YYYY-MM-DD.md",
      "preferred_editor": "Obsidian",
      "markdown_flavor": "Obsidian Markdown",
      "git_repository": {
        "remote_url": "https://github.com/itsmehari/myobsidian.git",
        "branch": "master",
        "auto_sync": true,
        "sync_script": "sync-vault.ps1",
        "quick_sync": "sync.bat"
      }
    },
    "ai_capabilities": {
      "file_operations": {
        "create_file": true,
        "read_files": true,
        "edit_files": true,
        "file_glob": true
      },
      "system_operations": {
        "run_command": true,
        "directory_navigation": true,
        "git_integration": true
      },
      "features": {
        "codebase_analysis": true,
        "technical_documentation": true,
        "project_management": true,
        "knowledge_management": true
      }
    },
    "quick_setup_commands": {
      "verify_vault": "Test-Path \"C:\\Users\\Admin\\Documents\\Obsidian Vault\"",
      "list_contents": "Get-ChildItem \"C:\\Users\\Admin\\Documents\\Obsidian Vault\" -Recurse -Name",
      "test_creation": "New-Item -Path \"C:\\Users\\Admin\\Documents\\Obsidian Vault\\AI-Test.md\" -ItemType File",
      "git_status": "cd \"C:\\Users\\Admin\\Documents\\Obsidian Vault\" && git status"
    },
    "integration_examples": [
      {
        "task": "Technical Analysis",
        "file_pattern": "[System]-Analysis-YYYY-MM-DD.md",
        "example": "BSERI-Blog-System-Analysis-2025-06-20.md"
      },
      {
        "task": "Project Documentation",
        "file_pattern": "Project-[Name]-[Component].md",
        "example": "Project-WebApp-Security-Audit.md"
      },
      {
        "task": "Daily Notes",
        "file_pattern": "YYYY-MM-DD-Daily-Notes.md",
        "example": "2025-06-20-Daily-Notes.md"
      }
    ],
    "handoff_instructions": {
      "step_1": "Load this configuration file to understand vault setup",
      "step_2": "Run initialization script from AI-Obsidian-Integration-Guide.md",
      "step_3": "Test file operations with create_file, read_files, edit_files",
      "step_4": "Verify git integration if repository is detected",
      "step_5": "Follow naming conventions and markdown standards"
    },
    "success_indicators": [
      "Can create files in vault directory",
      "Can read existing vault content",
      "Can edit and update files",
      "Maintains consistent formatting",
      "Uses proper Obsidian linking syntax",
      "Respects git workflow if applicable"
    ]
  }
}

